es_simple/__init__.py
es_simple/main.py
es_simple-0.0.7.dist-info/METADATA
es_simple-0.0.7.dist-info/WHEEL
es_simple-0.0.7.dist-info/licenses/LICENSE
es_simple-0.0.7.dist-info/RECORD
